{
  "main": {
    "id": "de481014610736a2",
    "type": "split",
    "children": [
      {
        "id": "52f81c2b5ba676b1",
        "type": "tabs",
        "children": [
          {
            "id": "f81d65f928e19824",
            "type": "leaf",
            "state": {
              "type": "markdown",
              "state": {
                "file": "Antropoloji-101.md",
                "mode": "source",
                "source": false
              },
              "icon": "lucide-file",
              "title": "Antropoloji-101"
            }
          }
        ]
      }
    ],
    "direction": "vertical"
  },
  "left": {
    "id": "9f61724af5d52c1c",
    "type": "split",
    "children": [
      {
        "id": "b48dbe10fb53d9f2",
        "type": "tabs",
        "children": [
          {
            "id": "fbea3f2fb62fe9b3",
            "type": "leaf",
            "state": {
              "type": "file-explorer",
              "state": {
                "sortOrder": "alphabetical",
                "autoReveal": false
              },
              "icon": "lucide-folder-closed",
              "title": "Files"
            }
          },
          {
            "id": "a5a40dc0b03a6e0e",
            "type": "leaf",
            "state": {
              "type": "search",
              "state": {
                "query": "",
                "matchingCase": false,
                "explainSearch": false,
                "collapseAll": false,
                "extraContext": false,
                "sortOrder": "alphabetical"
              },
              "icon": "lucide-search",
              "title": "Search"
            }
          },
          {
            "id": "f7a1845341bb56cb",
            "type": "leaf",
            "state": {
              "type": "bookmarks",
              "state": {},
              "icon": "lucide-bookmark",
              "title": "Bookmarks"
            }
          }
        ]
      }
    ],
    "direction": "horizontal",
    "width": 300
  },
  "right": {
    "id": "efe6d4463d0b5da1",
    "type": "split",
    "children": [
      {
        "id": "102a17d3b10b6836",
        "type": "tabs",
        "children": [
          {
            "id": "90d9a8013b2a8bed",
            "type": "leaf",
            "state": {
              "type": "backlink",
              "state": {
                "collapseAll": false,
                "extraContext": false,
                "sortOrder": "alphabetical",
                "showSearch": false,
                "searchQuery": "",
                "backlinkCollapsed": false,
                "unlinkedCollapsed": true
              },
              "icon": "links-coming-in",
              "title": "Backlinks"
            }
          },
          {
            "id": "fdf00eb42d04d0a4",
            "type": "leaf",
            "state": {
              "type": "outgoing-link",
              "state": {
                "linksCollapsed": false,
                "unlinkedCollapsed": true
              },
              "icon": "links-going-out",
              "title": "Outgoing links"
            }
          },
          {
            "id": "e2f581f41d2280a0",
            "type": "leaf",
            "state": {
              "type": "tag",
              "state": {
                "sortOrder": "frequency",
                "useHierarchy": true,
                "showSearch": false,
                "searchQuery": ""
              },
              "icon": "lucide-tags",
              "title": "Tags"
            }
          },
          {
            "id": "42e3343694481339",
            "type": "leaf",
            "state": {
              "type": "outline",
              "state": {
                "file": "hayatımı-düzene-sokuyom.md",
                "followCursor": false,
                "showSearch": false,
                "searchQuery": ""
              },
              "icon": "lucide-list",
              "title": "Outline of hayatımı-düzene-sokuyom"
            }
          }
        ]
      }
    ],
    "direction": "horizontal",
    "width": 300,
    "collapsed": true
  },
  "left-ribbon": {
    "hiddenItems": {
      "switcher:Open quick switcher": false,
      "graph:Open graph view": false,
      "canvas:Create new canvas": false,
      "daily-notes:Open today's daily note": false,
      "templates:Insert template": false,
      "command-palette:Open command palette": false
    }
  },
  "active": "f81d65f928e19824",
  "lastOpenFiles": [
    "antropoloji/örnek.md",
    "hayatimi-duzene-sokma-plani.md",
    "antropoloji/Antropoloji-101.md",
    "Antropoloji-101.md",
    "antropoloji",
    "toc.md",
    "oldu.md",
    "antro.md",
    "örnek.md",
    "antropology.md",
    "my-first-post.md"
  ]
}